pricer/__init__.py
pricer/analysis.py
pricer/campaign.py
pricer/config/general_settings.yaml
pricer/config/user_items.yaml
pricer/config/user_settings.yaml
pricer/config.py
pricer/io.py
pricer/reporting.py
pricer/run.py
pricer/schema.py
pricer/sources.py
pricer/utils.py
pricer/webserver/__init__.py
pricer/webserver/static/scripts.js
pricer/webserver/static/style.css
pricer/webserver/templates/home.html
pricer/webserver/templates/item_reporting.html
pricer/webserver/templates/template.html
pricer/webserver/views.py
pricer-0.5.5.dist-info/entry_points.txt
pricer-0.5.5.dist-info/LICENSE
pricer-0.5.5.dist-info/WHEEL
pricer-0.5.5.dist-info/METADATA
pricer-0.5.5.dist-info/RECORD
