Metadata-Version: 2.1
Name: pricer
Version: 0.5.5
Summary: Use WoW addon data to optimize auction buying and selling policies
Home-page: https://github.com/bluemania/wow_auctions
License: MIT
Author: bluemania
Author-email: damnthatswack@hotmail.com
Requires-Python: >=3.7,<4.0
Classifier: License :: OSI Approved :: MIT License
Classifier: Programming Language :: Python :: 3
Classifier: Programming Language :: Python :: 3.7
Classifier: Programming Language :: Python :: 3.8
Requires-Dist: PyYAML (==5.2)
Requires-Dist: SLPP (==1.2)
Requires-Dist: beautifulsoup4 (>=4.9.1,<5.0.0)
Requires-Dist: click (==6.7)
Requires-Dist: deepdiff (>=5.0.2,<6.0.0)
Requires-Dist: fastparquet (==0.3.3)
Requires-Dist: flask (>=1.1.2,<2.0.0)
Requires-Dist: importlib_metadata (>=1.7.0,<2.0.0)
Requires-Dist: matplotlib (>=3.3.2,<4.0.0)
Requires-Dist: pandas (>=1.1.4,<2.0.0)
Requires-Dist: pandera (>=0.4.5,<0.5.0)
Requires-Dist: requests (>=2.24.0,<3.0.0)
Requires-Dist: seaborn (==0.9.0)
Requires-Dist: selenium (>=3.141.0,<4.0.0)
Requires-Dist: sklearn (>=0.0,<0.1)
Requires-Dist: tqdm (>=4.49.0,<5.0.0)
Project-URL: Documentation, https://pricer.readthedocs.io/
Project-URL: Repository, https://github.com/bluemania/wow_auctions
